loadgui/__main__.py
loadgui/oscheck.py
loadgui-1.0.0.dist-info/LICENSE
loadgui-1.0.0.dist-info/METADATA
loadgui-1.0.0.dist-info/WHEEL
loadgui-1.0.0.dist-info/top_level.txt
loadgui-1.0.0.dist-info/RECORD
