Metadata-Version: 2.1
Name: loadgui
Version: 1.0.0
Summary: Build a loading screen for your project.
Author-email: Gorzan <gorzan0123@gmai.com>
License: Permission is hereby granted, free of charge, to any person obtaining a copy of this software and associated documentation files (the “Software”), to deal in the Software without restriction, including without limitation the rights to use, copy, modify, merge, publish, distribute, sublicense, and/or sell copies of the Software, and to permit persons to whom the Software is furnished to do so, subject to the following conditions:
Project-URL: Homepage, https://github.com/InfinityGorzan/load-screen
Keywords: loader,screen
Classifier: License :: OSI Approved :: MIT License
Classifier: Programming Language :: Python
Classifier: Programming Language :: Python :: 3
Requires-Python: >=3.8
License-File: LICENSE
Provides-Extra: dev
Requires-Dist: pip-tools ; extra == 'dev'
